hostspace/__init__.py
hostspace/cli.py
hostspace/env_commands.py
hostspace/auth/__init__.py
hostspace/auth/commands.py
hostspace/hcs/__init__.py
hostspace/hcs/commands.py
hostspace/hds/__init__.py
hostspace/hds/commands.py
hostspace/hke/__init__.py
hostspace/hke/commands.py
hostspace/utils/__init__.py
hostspace/utils/api.py
hostspace/utils/config.py
hostspace_cli-0.1.1.dist-info/METADATA
hostspace_cli-0.1.1.dist-info/WHEEL
hostspace_cli-0.1.1.dist-info/entry_points.txt
hostspace_cli-0.1.1.dist-info/top_level.txt
hostspace_cli-0.1.1.dist-info/RECORD
